Workbook

Sheet Guide
A1: Prospecteur 2.0 - CRM de prospection
A2: Ce classeur fonctionne dans Excel, Google Sheets et LibreOffice. Prospecteur 2.0 le met à jour pour vous ; vous pouvez aussi le modifier à la main.
A4: Les feuilles
A5: Prospects : une ligne par entreprise. L'ID (P-0001...) ne change jamais. Rouge = action en retard, jaune = action prévue aujourd'hui, gris = ne plus contacter ou refus définitif, vert = client gagné.
A6: Historique : une ligne par interaction. On n'efface jamais une ligne : l'historique complet reste disponible.
A7: Tableau de bord : les indicateurs du mois se calculent seuls. La période se règle dans Paramètres.
A8: Planification : la liste des actions en retard, du jour, de la semaine et du mois (régénérée par Prospecteur 2.0).
A9: Paramètres : cellules jaunes modifiables (objectifs, délais de relance, jours de prospection, congés). Ne pas renommer les en-têtes.
A10: Non-contact : toute personne ou entreprise qui a demandé à ne plus être contactée. Ne jamais supprimer une ligne de cette feuille.
A12: Règles d'or
A13: 1. Une entreprise = une seule ligne. Avant d'ajouter, chercher si elle existe déjà.
A14: 2. Une entreprise recherchée n'est pas une entreprise contactée : seule la date du premier contact compte pour l'objectif.
... A48: Notes :

Sheet Prospects
A1: ID | B1: Entreprise | C1: Site web | D1: Secteur d'activité | E1: Ville et région | F1: Contact professionnel | G1: Fonction | H1: Courriel professionnel | I1: Téléphone professionnel | J1: Source | K1: Date d'identification | L1: Objectif commercial | M1: Besoin ou problème observé | N1: Service recommandé | O1: Priorité | P1: Score de qualification | Q1: Statut commercial | R1: Date du premier contact | S1: Date du dernier contact | T1: Date de première réponse | U1: Canal du dernier contact | V1: Prochaine action | W1: Date de prochaine action | X1: Nombre de contacts | Y1: Objections rencontrées | Z1: Base de consentement | AA1: Valeur potentielle ($) | AB1: Résultat final | AC1: Motif de perte ou de refus | AD1: Notes

Sheet Historique
A1: ID prospect | B1: Entreprise | C1: Date et heure | D1: Canal | E1: Type d'action | F1: Résumé de l'échange | G1: Réponse reçue | H1: Objection | I1: Résultat | J1: Prochaine action | K1: Date de prochaine action

Sheet Tableau de bord
A1: Tableau de bord
A2: Période suivie : | B2: ='Paramètres'!$O$7 | C2: =EOMONTH(B2,0) | D2: (premier jour modifiable dans Paramètres)
A4: OBJECTIFS DU MOIS
A5: Objectif mensuel de premiers contacts | B5: ='Paramètres'!$O$2 | C5: Réglable dans Paramètres
A6: Objectif mensuel de rendez-vous | B6: ='Paramètres'!$O$3
A7: Objectif mensuel de propositions | B7: ='Paramètres'!$O$4
A8: Objectif mensuel de ventes | B8: ='Paramètres'!$O$5
A9: ACTIVITÉ DU MOIS
A10: Nouveaux prospects identifiés | B10: =COUNTIFS('Prospects'!$K$2:$K$10000,">="&$B$2,'Prospects'!$K$2:$K$10000,"<"&($C$2+1)) | C10: Recherchés, pas forcément contactés
A11: Premiers contacts effectués | B11: =COUNTIFS('Prospects'!$R$2:$R$10000,">="&$B$2,'Prospects'!$R$2:$R$10000,"<"&($C$2+1)) | C11: Seul ce chiffre compte pour l'objectif de contacts
A12: Relances réalisées | B12: =COUNTIFS('Historique'!$C$2:$C$10000,">="&$B$2,'Historique'!$C$2:$C$10000,"<"&($C$2+1),'Historique'!$E$2:$E$10000,"Relance")
A13: Prospects ayant répondu | B13: =COUNTIFS('Prospects'!$T$2:$T$10000,">="&$B$2,'Prospects'!$T$2:$T$10000,"<"&($C$2+1)) | C13: Première réponse de chaque prospect, comptée une seule fois
A14: Rendez-vous obtenus | B14: =COUNTIFS('Historique'!$C$2:$C$10000,">="&$B$2,'Historique'!$C$2:$C$10000,"<"&($C$2+1),'Historique'!$I$2:$I$10000,"Rendez-vous obtenu")
A15: Propositions envoyées | B15: =COUNTIFS('Historique'!$C$2:$C$10000,">="&$B$2,'Historique'!$C$2:$C$10000,"<"&($C$2+1),'Historique'!$I$2:$I$10000,"Proposition envoyée")
A16: Clients gagnés | B16: =COUNTIFS('Historique'!$C$2:$C$10000,">="&$B$2,'Historique'!$C$2:$C$10000,"<"&($C$2+1),'Historique'!$I$2:$I$10000,"Vente conclue")
A17: Refus définitifs et demandes de non-contact | B17: =COUNTIFS('Historique'!$C$2:$C$10000,">="&$B$2,'Historique'!$C$2:$C$10000,"<"&($C$2+1),'Historique'!$I$2:$I$10000,"Refus définitif")+COUNTIFS('Historique'!$C$2:$C$10000,">="&$B$2,'Historique'!$C$2:$C$10000,"<"&($C$2+1),'Historique'!$I$2:$I$10000,"Demande de non-contact")
A18: Chiffre d'affaires signé ($) | B18: =SUMIFS('Prospects'!$AA$2:$AA$10000,'Prospects'!$Q$2:$Q$10000,"Client gagné",'Prospects'!$S$2:$S$10000,">="&$B$2,'Prospects'!$S$2:$S$10000,"<"&($C$2+1)) | C18: Valeur des dossiers gagnés ce mois-ci, si elle est saisie
A19: TAUX DU MOIS
A20: Taux de réponse | B20: =IFERROR($B$13/$B$11,0) | C20: Prospects ayant répondu / premiers contacts du mois (approximation)
A21: Taux de rendez-vous | B21: =IFERROR($B$14/$B$11,0) | C21: Rendez-vous / premiers contacts
A22: Taux de conversion | B22: =IFERROR($B$16/$B$11,0) | C22: Ventes / premiers contacts
A23: Réalisation de l'objectif de contacts | B23: =IFERROR($B$11/$B$5,0)
A24: PIPELINE ET RETARDS (EN CE MOMENT)
A25: Prospects dans le CRM | B25: =COUNTA('Prospects'!$A$2:$A$10000)
A26: Prospects réellement contactés | B26: =COUNTIF('Prospects'!$X$2:$X$10000,">0") | C26: Un prospect recherché n'est pas un prospect contacté
A27: Prospects qualifiés ou plus | B27: =SUMPRODUCT(COUNTIFS('Paramètres'!$A$2:$A$40,'Prospects'!$Q$2:$Q$10000,'Paramètres'!$D$2:$D$40,"Oui"))
A28: Valeur du pipeline ($) | B28: =SUMPRODUCT(--(COUNTIFS('Paramètres'!$A$2:$A$40,'Prospects'!$Q$2:$Q$10000,'Paramètres'!$E$2:$E$40,"Oui")>0),'Prospects'!$AA$2:$AA$10000) | C28: Dossiers contactés et encore ouverts
A29: Actions en retard | B29: =SUMPRODUCT(('Prospects'!$W$2:$W$10000<>"")*('Prospects'!$W$2:$W$10000<TODAY())*(COUNTIFS('Paramètres'!$A$2:$A$40,'Prospects'!$Q$2:$Q$10000,'Paramètres'!$C$2:$C$40,"Oui")>0)) | C29: Dossiers ouverts dont la date d'action est passée
A30: Actions prévues aujourd'hui | B30: =SUMPRODUCT(('Prospects'!$W$2:$W$10000=TODAY())*(COUNTIFS('Paramètres'!$A$2:$A$40,'Prospects'!$Q$2:$Q$10000,'Paramètres'!$C$2:$C$40,"Oui")>0)) | C30: Relances et rendez-vous du jour
A31: RYTHME
A32: Jours de prospection restants (aujourd'hui inclus) | B32: =SUMPRODUCT((($B$2+ROW($1:$31)-1)>=MAX(TODAY(),$B$2))*(($B$2+ROW($1:$31)-1)<=$C$2)*(MID($B$35,WEEKDAY(($B$2+ROW($1:$31)-1),2),1)="0")*(COUNTIF('Paramètres'!$U$2:$U$60,($B$2+ROW($1:$31)-1))=0)) | C32: Selon les jours actifs et les congés de Paramètres
A33: Premiers contacts encore nécessaires | B33: =MAX(0,$B$5-$B$11)
A34: Rythme nécessaire par jour de prospection | B34: =IF($B$32=0,$B$33,ROUNDUP($B$33/$B$32,0)) | C34: Plan de rattrapage détaillé : demander le bilan
A35: Code des jours non travaillés (technique) | B35: =IF('Paramètres'!$S$2="Oui","0","1")&IF('Paramètres'!$S$3="Oui","0","1")&IF('Paramètres'!$S$4="Oui","0","1")&IF('Paramètres'!$S$5="Oui","0","1")&IF('Paramètres'!$S$6="Oui","0","1")&IF('Paramètres'!$S$7="Oui","0","1")&IF('Paramètres'!$S$8="Oui","0","1") | C35: Ne pas modifier

Sheet Planification
A1: Planification
A2: Cette feuille est régénérée par Prospecteur 2.0 (commande « planifier »). Les couleurs de la feuille Prospects, elles, se mettent à jour seules.

Sheet Paramètres
A1: Statuts | B1: Phase | C1: Ouvert (Oui/Non) | D1: Qualifié ou plus (Oui/Non) | E1: Dans le pipeline (Oui/Non) | G1: Canaux | H1: Types d'action | I1: Résultats | J1: Priorités | K1: Sources | L1: Bases de consentement | N1: Réglage | O1: Valeur | P1: Note | R1: Jour de prospection | S1: Actif (Oui/Non) | U1: Congés et jours fériés
A2: Prospect identifié | B2: 1. Préparation | C2: Oui | D2: Non | E2: Non | G2: Courriel | H2: Recherche | I2: Pas de réponse | J2: A - Haute | K2: Recherche Google | L2: Publication visible (adresse d'affaires publiée) | N2: Objectif mensuel - premiers contacts | O2: 100 | P2: Entreprises réellement contactées dans le mois | R2: Lundi | S2: Oui | U2: 46023
A3: Informations à vérifier | B3: 1. Préparation | C3: Oui | D3: Non | E3: Non | G3: Téléphone | H3: Premier contact | I3: Réponse positive | J3: B - Moyenne | K3: Google Maps | L3: Carte ou adresse remise par la personne | N3: Objectif mensuel - rendez-vous | O3: 10 | R3: Mardi | S3: Oui | U3: 46115
A4: Prospect qualifié | B4: 1. Préparation | C4: Oui | D4: Oui | E4: Non | G4: LinkedIn | H4: Relance | I4: Réponse neutre | J4: C - Basse | K4: Recommandation | L4: Relation d'affaires existante | N4: Objectif mensuel - propositions | O4: 5 | R4: Mercredi | S4: Oui | U4: 46160
A5: Approche à préparer | B5: 1. Préparation | C5: Oui | D5: Oui | E5: Non | G5: Formulaire du site | H5: Réponse du prospect | I5: Réponse négative | K5: LinkedIn | L5: Consentement exprès | N5: Objectif mensuel - ventes | O5: 2 | R5: Jeudi | S5: Oui | U5: 46197
A6: Prêt à contacter | B6: 2. Premier contact | C6: Oui | D6: Oui | E6: Non | G6: En personne | H6: Appel | I6: Rendez-vous obtenu | K6: Réseau personnel | L6: Appel B2B uniquement | N6: Objectif mensuel - chiffre d'affaires ($) | O6: 4000 | R6: Vendredi | S6: Oui | U6: 46204
A7: Premier contact effectué | B7: 2. Premier contact | C7: Oui | D7: Oui | E7: Oui | G7: SMS | H7: Rendez-vous | I7: Rendez-vous tenu | K7: Événement | L7: À vérifier | N7: Premier jour du mois suivi | O7: =DATE(YEAR(TODAY()),MONTH(TODAY()),1) | P7: Laisser la formule pour le mois en cours, ou saisir une date | R7: Samedi | S7: Non | U7: 46272
A8: En attente de réponse | B8: 3. Suivi initial | C8: Oui | D8: Oui | E8: Oui | G8: Messagerie (Facebook, Instagram) | H8: Proposition envoyée | I8: Absent au rendez-vous | K8: Annuaire | N8: Relance 1 (jours après le premier contact) | O8: 3 | R8: Dimanche | S8: Non | U8: 46307
A9: Relance à effectuer | B9: 3. Suivi initial | C9: Oui | D9: Oui | E9: Oui | G9: Visioconférence | H9: Négociation | I9: Devis demandé | K9: Site web du prospect | N9: Relance 2 (jours après le premier contact) | O9: 7 | U9: 46381
A10: Réponse reçue | B10: 3. Suivi initial | C10: Oui | D10: Oui | E10: Oui | G10: Autre | H10: Note interne | I10: Proposition envoyée | K10: Entrant (il nous a contactés) | N10: Relance 3 - dernière de la séquence (jours) | O10: 14 | U10: 46388
A11: Rendez-vous à planifier | B11: 4. Qualification et rendez-vous | C11: Oui | D11: Oui | E11: Oui | H11: Clôture | I11: Négociation | K11: Autre | N11: Mise en sommeil après la séquence (jours) | O11: 90 | P11: Délai avant une reprise de contact sans réponse | U11: 46472
A12: Rendez-vous confirmé | B12: 4. Qualification et rendez-vous | C12: Oui | D12: Oui | E12: Oui | I12: Vente conclue | N12: Tentatives après réveil avant clôture | O12: 1 | P12: Au-delà, le dossier passe à Perdu (aucune réponse) | U12: 46531
A13: Besoin à analyser | B13: 4. Qualification et rendez-vous | C13: Oui | D13: Oui | E13: Oui | I13: Refus définitif | N13: Score minimum pour contacter (sur 100) | O13: 50 | P13: En dessous : approfondir ou abandonner | U13: 46562
A14: Proposition commerciale à préparer | B14: 5. Proposition et négociation | C14: Oui | D14: Oui | E14: Oui | I14: Report demandé | N14: Valeur moyenne d'un contrat ($) | O14: 2000 | P14: Hypothèse utilisée quand la valeur est inconnue | U14: 46569
A15: Proposition envoyée | B15: 5. Proposition et négociation | C15: Oui | D15: Oui | E15: Oui | I15: Demande de non-contact | U15: 46636
A16: Négociation en cours | B16: 5. Proposition et négociation | C16: Oui | D16: Oui | E16: Oui | I16: Autre | N16: Les cellules jaunes se modifient librement. Ne pas renommer les en-têtes : le moteur s'en sert. | U16: 46671
A17: Client gagné | B17: 6. Conclusion | C17: Non | D17: Oui | E17: Non | U17: 46746
A18: Prospect à recontacter ultérieurement | B18: 6. Conclusion | C18: Oui | D18: Oui | E18: Non
A19: Perdu | B19: 6. Conclusion | C19: Non | D19: Oui | E19: Non
A20: Refus définitif | B20: 6. Conclusion | C20: Non | D20: Oui | E20: Non
A21: Ne plus contacter | B21: 6. Conclusion | C21: Non | D21: Oui | E21: Non

Sheet Non-contact
A1: Date de la demande | B1: ID prospect | C1: Entreprise | D1: Contact | E1: Courriel | F1: Téléphone | G1: Domaine | H1: Portée | I1: Canal de la demande | J1: Notes
